cakoo/__init__.py
cakoo/cli.py
cakoo-0.1.1.dist-info/METADATA
cakoo-0.1.1.dist-info/WHEEL
cakoo-0.1.1.dist-info/entry_points.txt
cakoo-0.1.1.dist-info/top_level.txt
cakoo-0.1.1.dist-info/RECORD
