Metadata-Version: 2.4
Name: cakoo
Version: 0.1.1
Summary: cakoo CLI - Cross-platform C++ dev setup tool with colorful terminal UI
Author: Vishal Ahirwar
License-Expression: MIT
Requires-Dist: rich>=13.0
